skpdtree/__init__.py
skpdtree/dtree.py
skpdtree-0.0.3.dist-info/METADATA
skpdtree-0.0.3.dist-info/WHEEL
skpdtree-0.0.3.dist-info/licenses/LICENSE
skpdtree-0.0.3.dist-info/RECORD
