Metadata-Version: 2.1
Name: skpdtree
Version: 0.0.3
Summary: Machine Learning
Author: Subir Kumar Patro
License: Copyright (c) 2022 SUBIR
License-File: LICENSE
Classifier: License :: OSI Approved :: MIT License
Classifier: Operating System :: OS Independent
Classifier: Programming Language :: Python :: 3
Requires-Python: >=3.7
